HelloWorldhahaha/__init__.py
HelloWorldhahaha/hello_world.py
HelloWorldhahaha-0.0.0.2.dist-info/METADATA
HelloWorldhahaha-0.0.0.2.dist-info/WHEEL
HelloWorldhahaha-0.0.0.2.dist-info/top_level.txt
HelloWorldhahaha-0.0.0.2.dist-info/RECORD
