Metadata-Version: 2.1
Name: HelloWorldhahaha
Version: 0.0.0.2
Summary: hello world package.
Home-page: 
Author: 
Author-email: 
License: MIT
Requires-Python: >=3.4
Requires-Dist: boto3
Requires-Dist: pymongo
